kotemari/__init__.py
kotemari/core.py
kotemari/controller/cli_controller.py
kotemari/domain/__init__.py
kotemari/domain/context_data.py
kotemari/domain/dependency_info.py
kotemari/domain/exceptions.py
kotemari/domain/file_content_formatter.py
kotemari/domain/file_info.py
kotemari/domain/file_system_event.py
kotemari/domain/parsed_python_info.py
kotemari/domain/project_config.py
kotemari/gateway/cli_parser.py
kotemari/gateway/file_system_accessor.py
kotemari/gateway/gitignore_reader.py
kotemari/service/__init__.py
kotemari/service/ast_parser.py
kotemari/service/file_system_event_monitor.py
kotemari/service/hash_calculator.py
kotemari/service/ignore_rule_processor.py
kotemari/service/language_detector.py
kotemari/service/python_parser.py
kotemari/usecase/__init__.py
kotemari/usecase/config_manager.py
kotemari/usecase/context_builder.py
kotemari/usecase/project_analyzer.py
kotemari/utility/path_resolver.py
kotemari-0.1.0.dist-info/METADATA
kotemari-0.1.0.dist-info/WHEEL
kotemari-0.1.0.dist-info/entry_points.txt
kotemari-0.1.0.dist-info/licenses/LICENSE
kotemari-0.1.0.dist-info/RECORD
