Metadata-Version: 2.4
Name: kotemari
Version: 0.1.0
Summary: Kotemari: A Python library and CLI tool to analyze codebases, understand dependencies, and generate accurate context for LLMs. Simplifies RAG generation for coding tasks.
Project-URL: Homepage, https://github.com/your-username/kotemari
Project-URL: Bug Tracker, https://github.com/your-username/kotemari/issues
Project-URL: Repository, https://github.com/your-username/kotemari
Author-email: Your Name <your.email@example.com>
License-File: LICENSE
Keywords: context generation,dependency,llm,project analysis,python
Classifier: Development Status :: 3 - Alpha
Classifier: Intended Audience :: Developers
Classifier: License :: OSI Approved :: MIT License
Classifier: Operating System :: OS Independent
Classifier: Programming Language :: Python :: 3
Classifier: Topic :: Software Development :: Build Tools
Classifier: Topic :: Software Development :: Libraries :: Python Modules
Classifier: Topic :: Utilities
Requires-Python: >=3.9
Requires-Dist: pathspec>=0.12
Requires-Dist: pyyaml>=6.0
Requires-Dist: rich>=14.0.0
Requires-Dist: typer[all]>=0.15.2
Requires-Dist: watchdog>=3.0.0
Provides-Extra: dev
Requires-Dist: pytest-cov>=4.1.0; extra == 'dev'
Requires-Dist: pytest-mock>=3.10.0; extra == 'dev'
Requires-Dist: pytest>=8.3.0; extra == 'dev'
Requires-Dist: uv>=0.1.0; extra == 'dev'
